Metadata-Version: 2.1
Name: nanoStringPy
Version: 0.0.1
Summary: Python package to analyze nanostring mRNA data
Author: Rudramani Pokhrel
